makemcp/__init__.py
makemcp/autodiscovery.py
makemcp/cli.py
makemcp/cli_factory.py
makemcp/decorators.py
makemcp/quick.py
makemcp/registry.py
makemcp/server.py
makemcp/types.py
makemcp/factory/__init__.py
makemcp/factory/config.py
makemcp/factory/core.py
makemcp/factory/errors.py
makemcp/factory/import_analyzer.py
makemcp/factory/type_conversion.py
makemcp/factory/utils.py
makemcp/factory/wrappers.py
makemcp-0.1.0.dist-info/METADATA
makemcp-0.1.0.dist-info/WHEEL
makemcp-0.1.0.dist-info/entry_points.txt
makemcp-0.1.0.dist-info/RECORD
