Metadata-Version: 2.4
Name: makemcp
Version: 0.1.0
Summary: A lightweight, easy-to-use wrapper for creating MCP (Model Context Protocol) servers in Python
Project-URL: Homepage, https://github.com/leifmarkthaler/makemcp
Project-URL: Documentation, https://github.com/leifmarkthaler/makemcp#readme
Project-URL: Repository, https://github.com/leifmarkthaler/makemcp
Project-URL: Issues, https://github.com/leifmarkthaler/makemcp/issues
Author: MakeMCP Contributors
License: MIT
Keywords: ai,llm,mcp,model-context-protocol,server
Classifier: Development Status :: 3 - Alpha
Classifier: Intended Audience :: Developers
Classifier: License :: OSI Approved :: MIT License
Classifier: Programming Language :: Python :: 3
Classifier: Programming Language :: Python :: 3.8
Classifier: Programming Language :: Python :: 3.9
Classifier: Programming Language :: Python :: 3.10
Classifier: Programming Language :: Python :: 3.11
Classifier: Programming Language :: Python :: 3.12
Classifier: Topic :: Scientific/Engineering :: Artificial Intelligence
Classifier: Topic :: Software Development :: Libraries :: Python Modules
Requires-Python: >=3.8
Requires-Dist: mcp>=0.1.0
Requires-Dist: pydantic>=2.0.0
Requires-Dist: pyyaml>=6.0.0
Requires-Dist: typing-extensions>=4.0.0
Provides-Extra: all
Requires-Dist: black>=23.0.0; extra == 'all'
Requires-Dist: mypy>=1.0.0; extra == 'all'
Requires-Dist: pytest-asyncio>=0.21.0; extra == 'all'
Requires-Dist: pytest>=7.0.0; extra == 'all'
Requires-Dist: ruff>=0.1.0; extra == 'all'
Requires-Dist: starlette>=0.27.0; extra == 'all'
Requires-Dist: uvicorn>=0.20.0; extra == 'all'
Provides-Extra: dev
Requires-Dist: black>=23.0.0; extra == 'dev'
Requires-Dist: mypy>=1.0.0; extra == 'dev'
Requires-Dist: pytest-asyncio>=0.21.0; extra == 'dev'
Requires-Dist: pytest>=7.0.0; extra == 'dev'
Requires-Dist: ruff>=0.1.0; extra == 'dev'
Provides-Extra: http
Requires-Dist: starlette>=0.27.0; extra == 'http'
Requires-Dist: uvicorn>=0.20.0; extra == 'http'
